MANIFEST.in
README.rst
setup.py
docs/HISTORY.txt
rer/__init__.py
rer.downloadurl.egg-info/PKG-INFO
rer.downloadurl.egg-info/SOURCES.txt
rer.downloadurl.egg-info/dependency_links.txt
rer.downloadurl.egg-info/entry_points.txt
rer.downloadurl.egg-info/namespace_packages.txt
rer.downloadurl.egg-info/not-zip-safe
rer.downloadurl.egg-info/requires.txt
rer.downloadurl.egg-info/top_level.txt
rer/downloadurl/__init__.py
rer/downloadurl/configure.zcml
rer/downloadurl/interfaces.py
rer/downloadurl/setuphandlers.py
rer/downloadurl/skins.zcml
rer/downloadurl/Extensions/install.py
rer/downloadurl/profiles/default/browserlayer.xml
rer/downloadurl/profiles/default/metadata.xml
rer/downloadurl/profiles/default/skins.xml
rer/downloadurl/profiles/uninstall/browserlayer.xml
rer/downloadurl/profiles/uninstall/skins.xml
rer/downloadurl/skins/rer_downloadurl_custom_templates/file_view.pt
rer/downloadurl/skins/rer_downloadurl_custom_templates/file_view.pt.metadata
rer/downloadurl/skins/rer_downloadurl_custom_templates/image_view.pt
rer/downloadurl/skins/rer_downloadurl_custom_templates/image_view.pt.metadata