Metadata-Version: 1.1
Name: rer.downloadurl
Version: 2.0.0
Summary: Fix the download url of Plone files, adding also the file name to it
Home-page: http://plone.org/products/rer.downloadurl
Author: Redturtle Technology
Author-email: sviluppoplone@redturtle.it
License: GPL
Keywords: file download url plone plonegov
Platform: UNKNOWN
Classifier: Programming Language :: Python
Classifier: Framework :: Plone
Classifier: Framework :: Plone :: 4.2
